slicetime/__init__.py
slicetime/extract_slicetimes.py
slicetime/main.py
slicetime/make_image_stack.py
slicetime/nipype_interface.py
slicetime/tseriesinterp.py
pyslicetime-0.2.dist-info/METADATA
pyslicetime-0.2.dist-info/WHEEL
pyslicetime-0.2.dist-info/top_level.txt
pyslicetime-0.2.dist-info/RECORD
